sudreg/__init__.py
sudreg/sudreg.py
SudReg-1.0.2.dist-info/LICENSE.md
SudReg-1.0.2.dist-info/METADATA
SudReg-1.0.2.dist-info/WHEEL
SudReg-1.0.2.dist-info/top_level.txt
SudReg-1.0.2.dist-info/RECORD
