Metadata-Version: 2.1
Name: SudReg
Version: 1.0.2
Summary: A light weight Python library for the SudReg Web API
Home-page: https://github.com/0xe20x8d0xbc/sudreg
Author: Your Name
Author-email: 0xe20x8d0xbc@gmail.com
Keywords: Sudski Registar,Sudski Registar API
License-File: LICENSE.md
Requires-Dist: requests
